AUTHORS.rst
CHANGELOG.rst
LICENSE
MANIFEST.in
README.rst
setup.py
everlytic/__init__.py
everlytic/api.py
everlytic/models.py
everlytic/tasks.py
everlytic/tests.py
everlytic/migrations/0001_initial.py
everlytic/migrations/0001_initial.pyc
everlytic/migrations/0002_auto__chg_field_everlyticprofile_everlytic_id__add_unique_everlyticpro.py
everlytic/migrations/0002_auto__chg_field_everlyticprofile_everlytic_id__add_unique_everlyticpro.pyc
everlytic/migrations/__init__.py
everlytic/migrations/__init__.pyc
jmbo_everlytic.egg-info/PKG-INFO
jmbo_everlytic.egg-info/SOURCES.txt
jmbo_everlytic.egg-info/dependency_links.txt
jmbo_everlytic.egg-info/not-zip-safe
jmbo_everlytic.egg-info/requires.txt
jmbo_everlytic.egg-info/top_level.txt